odoo8_addon_vertical_ngo-8.0.0.1.0-py2.7-nspkg.pth
odoo_addons/vertical_ngo/__openerp__.py
odoo_addons/vertical_ngo/__init__.py
odoo_addons/vertical_ngo/README.rst
odoo_addons/vertical_ngo/view/vertical_ngo.xml
odoo_addons/vertical_ngo/models/res_config.py
odoo_addons/vertical_ngo/models/__init__.py
odoo_addons/vertical_ngo/i18n/vertical_ngo.pot
odoo_addons/vertical_ngo/static/description/icon.svg
odoo_addons/vertical_ngo/static/description/index.html
odoo_addons/vertical_ngo/static/description/vertical-ngo-settings.png
odoo_addons/vertical_ngo/static/description/vertical-ngo_LR.png
odoo_addons/vertical_ngo/static/description/icon.png
odoo8_addon_vertical_ngo-8.0.0.1.0.dist-info/top_level.txt
odoo8_addon_vertical_ngo-8.0.0.1.0.dist-info/WHEEL
odoo8_addon_vertical_ngo-8.0.0.1.0.dist-info/RECORD
odoo8_addon_vertical_ngo-8.0.0.1.0.dist-info/metadata.json
odoo8_addon_vertical_ngo-8.0.0.1.0.dist-info/DESCRIPTION.rst
odoo8_addon_vertical_ngo-8.0.0.1.0.dist-info/METADATA
odoo8_addon_vertical_ngo-8.0.0.1.0.dist-info/namespace_packages.txt
